{
  "project_info": {
    "project_number": "917201469983",
    "project_id": "strashcart",
    "storage_bucket": "strashcart.appspot.com"
  },
  "client": [
    {
      "client_info": {
        "mobilesdk_app_id": "1:917201469983:android:f3db2a95267ab07a0b0b2a",
        "android_client_info": {
          "package_name": "com.example.strash_cart"
        }
      },
      "oauth_client": [
        {
          "client_id": "917201469983-hpff9i4buhgmtr24o23d57jctghavp9u.apps.googleusercontent.com",
          "client_type": 3
        }
      ],
      "api_key": [
        {
          "current_key": "AIzaSyDRNiLox99XX59NC9SFQn7fqM7RMVEZ9zo"
        }
      ],
      "services": {
        "appinvite_service": {
          "other_platform_oauth_client": [
            {
              "client_id": "917201469983-hpff9i4buhgmtr24o23d57jctghavp9u.apps.googleusercontent.com",
              "client_type": 3
            }
          ]
        }
      }
    }
  ],
  "configuration_version": "1"
}